<annotation>
	<folder>apis</folder>
	<filename>93054073-grupo-de-abeja-o-abeja-en-latín-apis-mellifera-europeo-o-occidental-abeja-de-miel-aislados-en-el-fondo.jpg</filename>
	<path>C:\Users\karto\Desktop\chaquetas\apis\93054073-grupo-de-abeja-o-abeja-en-latín-apis-mellifera-europeo-o-occidental-abeja-de-miel-aislados-en-el-fondo.jpg</path>
	<source>
		<database>Unknown</database>
	</source>
	<size>
		<width>1300</width>
		<height>1006</height>
		<depth>3</depth>
	</size>
	<segmented>0</segmented>
	<object>
		<name>bee</name>
		<pose>Unspecified</pose>
		<truncated>0</truncated>
		<difficult>0</difficult>
		<bndbox>
			<xmin>76</xmin>
			<ymin>84</ymin>
			<xmax>526</xmax>
			<ymax>390</ymax>
		</bndbox>
	</object>
	<object>
		<name>bee</name>
		<pose>Unspecified</pose>
		<truncated>0</truncated>
		<difficult>0</difficult>
		<bndbox>
			<xmin>797</xmin>
			<ymin>45</ymin>
			<xmax>1156</xmax>
			<ymax>422</ymax>
		</bndbox>
	</object>
	<object>
		<name>bee</name>
		<pose>Unspecified</pose>
		<truncated>0</truncated>
		<difficult>0</difficult>
		<bndbox>
			<xmin>69</xmin>
			<ymin>661</ymin>
			<xmax>580</xmax>
			<ymax>901</ymax>
		</bndbox>
	</object>
	<object>
		<name>bee</name>
		<pose>Unspecified</pose>
		<truncated>0</truncated>
		<difficult>0</difficult>
		<bndbox>
			<xmin>465</xmin>
			<ymin>358</ymin>
			<xmax>883</xmax>
			<ymax>682</ymax>
		</bndbox>
	</object>
	<object>
		<name>bee</name>
		<pose>Unspecified</pose>
		<truncated>0</truncated>
		<difficult>0</difficult>
		<bndbox>
			<xmin>700</xmin>
			<ymin>635</ymin>
			<xmax>1245</xmax>
			<ymax>918</ymax>
		</bndbox>
	</object>
</annotation>
